{"_index":"bahnhoefept","_type":"bahnhofpt","_id":"AWYKOluzxpPIvaVA5ArP","_score":1,"_source":{"type":"Feature","geometry":{"type":"Point","coordinates":[-8.1941803,39.4402867]},"properties":{"name":"Abrantes","UICIBNR":9452001,"DBIBNR":9400005,"abkuerzung":"NTES","countryCode":"PT"}}}
{"_index":"bahnhoefept","_type":"bahnhofpt","_id":"AWYKOluzxpPIvaVA5ArS","_score":1,"_source":{"type":"Feature","geometry":{"type":"Point","coordinates":[-8.6510762,41.0502627]},"properties":{"name":"Aguda","UICIBNR":9439057,"DBIBNR":9400093,"abkuerzung":"GUDA","countryCode":"PT"}}}
{"_index":"bahnhoefept","_type":"bahnhofpt","_id":"AWYKOluzxpPIvaVA5ArV","_score":1,"_source":{"type":"Feature","geometry":{"type":"Point","coordinates":[-8.5891861,39.7935425]},"properties":{"name":"Albergaria dos Doze","UICIBNR":9434439,"DBIBNR":9400097,"abkuerzung":"DOZE","countryCode":"PT"}}}
{"_index":"bahnhoefept","_type":"bahnhofpt","_id":"AWYKOluzxpPIvaVA5Arg","_score":1,"_source":{"type":"Feature","geometry":{"type":"Point","coordinates":[-9.2289062,38.6983597]},"properties":{"name":"Algés","UICIBNR":9469088,"DBIBNR":9400019,"abkuerzung":"LGES","countryCode":"PT"}}}
{"_index":"bahnhoefept","_type":"bahnhofpt","_id":"AWYKOlu0xpPIvaVA5Arh","_score":1,"_source":{"type":"Feature","geometry":{"type":"Point","coordinates":[-8.3031978,37.1679084]},"properties":{"name":"Algoz","UICIBNR":9490050,"DBIBNR":9400111,"abkuerzung":"LGOZ","countryCode":"PT"}}}
{"_index":"bahnhoefept","_type":"bahnhofpt","_id":"AWYKOlu0xpPIvaVA5Arq","_score":1,"_source":{"type":"Feature","geometry":{"type":"Point","coordinates":[-7.998862,38.232282]},"properties":{"name":"Alvito","UICIBNR":9474351,"DBIBNR":9400125,"abkuerzung":"VITO","countryCode":"PT"}}}
{"_index":"bahnhoefept","_type":"bahnhofpt","_id":"AWYKOlu0xpPIvaVA5Art","_score":1,"_source":{"type":"Feature","geometry":{"type":"Point","coordinates":[-8.0074491,41.106412]},"properties":{"name":"Aregos","UICIBNR":9409191,"DBIBNR":9400136,"abkuerzung":"EGOS","countryCode":"PT"}}}
{"_index":"bahnhoefept","_type":"bahnhofpt","_id":"AWYKOlu0xpPIvaVA5Arx","_score":1,"_source":{"type":"Feature","geometry":{"type":"Point","coordinates":[-8.5009939,40.9092192]},"properties":{"name":"Arrifana","UICIBNR":9444248,"DBIBNR":9400140,"abkuerzung":"FANA","countryCode":"PT"}}}
{"_index":"bahnhoefept","_type":"bahnhofpt","_id":"AWYKOlu0xpPIvaVA5Ary","_score":1,"_source":{"type":"Feature","geometry":{"type":"Point","coordinates":[-8.5853435,40.8084504]},"properties":{"name":"Avanca","UICIBNR":9438216,"DBIBNR":9400144,"abkuerzung":"ANCA","countryCode":"PT"}}}
{"_index":"bahnhoefept","_type":"bahnhofpt","_id":"AWYKOlu0xpPIvaVA5Ar5","_score":1,"_source":{"type":"Feature","geometry":{"type":"Point","coordinates":[-7.835636,39.525381]},"properties":{"name":"Barca da Amieira-Envendos","UICIBNR":9452415,"DBIBNR":9400153,"abkuerzung":"NDOS","countryCode":"PT"}}}
{"_index":"bahnhoefept","_type":"bahnhofpt","_id":"AWYKOlu0xpPIvaVA5AsA","_score":1,"_source":{"type":"Feature","geometry":{"type":"Point","coordinates":[-8.5262247,41.3894912]},"properties":{"name":"Barrimau","UICIBNR":9405058,"DBIBNR":9400160,"abkuerzung":"IMAU","countryCode":"PT"}}}
{"_index":"bahnhoefept","_type":"bahnhofpt","_id":"AWYKOlu0xpPIvaVA5AsD","_score":1,"_source":{"type":"Feature","geometry":{"type":"Point","coordinates":[-9.1980215,38.6961686]},"properties":{"name":"Belém","UICIBNR":9469054,"DBIBNR":9400163,"abkuerzung":"ELEM","countryCode":"PT"}}}
{"_index":"bahnhoefept","_type":"bahnhofpt","_id":"AWYKOlu0xpPIvaVA5AsE","_score":1,"_source":{"type":"Feature","geometry":{"type":"Point","coordinates":[-7.958793,39.492067]},"properties":{"name":"Belver","UICIBNR":9452282,"DBIBNR":9400165,"abkuerzung":"LVER","countryCode":"PT"}}}
{"_index":"bahnhoefept","_type":"bahnhofpt","_id":"AWYKOlu0xpPIvaVA5AsI","_score":1,"_source":{"type":"Feature","geometry":{"type":"Point","coordinates":[-8.764438,40.122318]},"properties":{"name":"Bifurcacao de Lares","UICIBNR":9464022,"DBIBNR":9400174,"abkuerzung":"ARES","countryCode":"PT"}}}
{"_index":"bahnhoefept","_type":"bahnhofpt","_id":"AWYKOlu0xpPIvaVA5AsL","_score":1,"_source":{"type":"Feature","geometry":{"type":"Point","coordinates":[-7.922121,37.013893]},"properties":{"name":"Bom Joao","UICIBNR":9473031,"DBIBNR":9400178,"abkuerzung":"JOAO","countryCode":"PT"}}}
{"_index":"bahnhoefept","_type":"bahnhofpt","_id":"AWYKOlu0xpPIvaVA5AsM","_score":1,"_source":{"type":"Feature","geometry":{"type":"Point","coordinates":[-9.1537119,39.2649007]},"properties":{"name":"Bombarral","UICIBNR":9462703,"DBIBNR":9400025,"abkuerzung":"RRAL","countryCode":"PT"}}}
{"_index":"bahnhoefept","_type":"bahnhofpt","_id":"AWYKOlu0xpPIvaVA5Asc","_score":1,"_source":{"type":"Feature","geometry":{"type":"Point","coordinates":[-8.4377894,41.3636918]},"properties":{"name":"Caniços","UICIBNR":9428100,"DBIBNR":9400207,"abkuerzung":"ICOS","countryCode":"PT"}}}
{"_index":"bahnhoefept","_type":"bahnhofpt","_id":"AWYKOlu0xpPIvaVA5Asf","_score":1,"_source":{"type":"Feature","geometry":{"type":"Point","coordinates":[-8.462838,39.5486161]},"properties":{"name":"Carrascal-Delongo","UICIBNR":9440030,"DBIBNR":9400212,"abkuerzung":"ONGO","countryCode":"PT"}}}
{"_index":"bahnhoefept","_type":"bahnhofpt","_id":"AWYKOlu1xpPIvaVA5Asi","_score":1,"_source":{"type":"Feature","geometry":{"type":"Point","coordinates":[-8.0074947,40.4332389]},"properties":{"name":"Carregal do Sal","UICIBNR":9446482,"DBIBNR":9400216,"abkuerzung":"OSAL","countryCode":"PT"}}}
{"_index":"bahnhoefept","_type":"bahnhofpt","_id":"AWYKOlu1xpPIvaVA5Asj","_score":1,"_source":{"type":"Feature","geometry":{"type":"Point","coordinates":[-8.564177,41.4869231]},"properties":{"name":"Carreira","UICIBNR":9406056,"DBIBNR":9400217,"abkuerzung":"EIRA","countryCode":"PT"}}}
{"_index":"bahnhoefept","_type":"bahnhofpt","_id":"AWYKOlu1xpPIvaVA5Asm","_score":1,"_source":{"type":"Feature","geometry":{"type":"Point","coordinates":[-8.6260591,40.9248032]},"properties":{"name":"Carvalheira-Maceda","UICIBNR":9438356,"DBIBNR":9400220,"abkuerzung":"CEDA","countryCode":"PT"}}}
{"_index":"bahnhoefept","_type":"bahnhofpt","_id":"AWYKOlu1xpPIvaVA5Aso","_score":1,"_source":{"type":"Feature","geometry":{"type":"Point","coordinates":[-8.1581887,38.4982896]},"properties":{"name":"Casa Branca","UICIBNR":9474005,"DBIBNR":9400029,"abkuerzung":"ANCA","countryCode":"PT"}}}
{"_index":"bahnhoefept","_type":"bahnhofpt","_id":"AWYKOlu1xpPIvaVA5Asq","_score":1,"_source":{"type":"Feature","geometry":{"type":"Point","coordinates":[-8.487906,40.5794322]},"properties":{"name":"Casal do Álvaro","UICIBNR":9442168,"DBIBNR":9400226,"abkuerzung":"VARO","countryCode":"PT"}}}
{"_index":"bahnhoefept","_type":"bahnhofpt","_id":"AWYKOlu1xpPIvaVA5Asu","_score":1,"_source":{"type":"Feature","geometry":{"type":"Point","coordinates":[-7.4909,39.81807]},"properties":{"name":"Castelo Branco","UICIBNR":9453009,"DBIBNR":9400229,"abkuerzung":"ANCO","countryCode":"PT"}}}
{"_index":"bahnhoefept","_type":"bahnhofpt","_id":"AWYKOlu1xpPIvaVA5Asv","_score":1,"_source":{"type":"Feature","geometry":{"type":"Point","coordinates":[-7.461139,40.064226]},"properties":{"name":"Castelo Novo","UICIBNR":9453314,"DBIBNR":9400236,"abkuerzung":"NOVO","countryCode":"PT"}}}
{"_index":"bahnhoefept","_type":"bahnhofpt","_id":"AWYKOlu1xpPIvaVA5Asx","_score":1,"_source":{"type":"Feature","geometry":{"type":"Point","coordinates":[-8.5374595,40.9395762]},"properties":{"name":"Cavaco","UICIBNR":9444172,"DBIBNR":9400239,"abkuerzung":"VACO","countryCode":"PT"}}}
{"_index":"bahnhoefept","_type":"bahnhofpt","_id":"AWYKOlu1xpPIvaVA5As0","_score":1,"_source":{"type":"Feature","geometry":{"type":"Point","coordinates":[-7.3824176,40.6651857]},"properties":{"name":"Celorico da Beira","UICIBNR":9448405,"DBIBNR":9400245,"abkuerzung":"EIRA","countryCode":"PT"}}}
{"_index":"bahnhoefept","_type":"bahnhofpt","_id":"AWYKOlu1xpPIvaVA5As3","_score":1,"_source":{"type":"Feature","geometry":{"type":"Point","coordinates":[-8.4321828,40.2089072]},"properties":{"name":"Coimbra","UICIBNR":9441020,"DBIBNR":9400012,"abkuerzung":"MBRA","countryCode":"PT"}}}
{"_index":"bahnhoefept","_type":"bahnhofpt","_id":"AWYKOlu1xpPIvaVA5As4","_score":1,"_source":{"type":"Feature","geometry":{"type":"Point","coordinates":[-8.4403418,40.2247344]},"properties":{"name":"Coimbra-B","UICIBNR":9436004,"DBIBNR":9400253,"abkuerzung":"BRAB","countryCode":"PT"}}}
{"_index":"bahnhoefept","_type":"bahnhofpt","_id":"AWYKOlu1xpPIvaVA5As5","_score":1,"_source":{"type":"Feature","geometry":{"type":"Point","coordinates":[-8.6339639,41.124353]},"properties":{"name":"Coimbrões","UICIBNR":9439149,"DBIBNR":9400254,"abkuerzung":"ROES","countryCode":"PT"}}}
{"_index":"bahnhoefept","_type":"bahnhofpt","_id":"AWYKOlu1xpPIvaVA5AtF","_score":1,"_source":{"type":"Feature","geometry":{"type":"Point","coordinates":[-8.3555057,41.3678299]},"properties":{"name":"Cuca","UICIBNR":9428209,"DBIBNR":9400276,"abkuerzung":"CUCA","countryCode":"PT"}}}
{"_index":"bahnhoefept","_type":"bahnhofpt","_id":"AWYKOlu1xpPIvaVA5AtP","_score":1,"_source":{"type":"Feature","geometry":{"type":"Point","coordinates":[-8.4737704,39.4616253]},"properties":{"name":"Entroncamento","UICIBNR":9434009,"DBIBNR":9400010,"abkuerzung":"ENTO","countryCode":"PT"}}}
{"_index":"bahnhoefept","_type":"bahnhofpt","_id":"AWYKOlu1xpPIvaVA5AtU","_score":1,"_source":{"type":"Feature","geometry":{"type":"Point","coordinates":[-8.6180012,40.6414734]},"properties":{"name":"Esgueira","UICIBNR":9442028,"DBIBNR":9400294,"abkuerzung":"EIRA","countryCode":"PT"}}}
{"_index":"bahnhoefept","_type":"bahnhofpt","_id":"AWYKOlu1xpPIvaVA5AtW","_score":1,"_source":{"type":"Feature","geometry":{"type":"Point","coordinates":[-8.902518,39.0507662]},"properties":{"name":"Espadanal da Azambuja","UICIBNR":9431401,"DBIBNR":9400296,"abkuerzung":"BUJA","countryCode":"PT"}}}
{"_index":"bahnhoefept","_type":"bahnhofpt","_id":"AWYKOlu1xpPIvaVA5Atf","_score":1,"_source":{"type":"Feature","geometry":{"type":"Point","coordinates":[-9.079914,39.535754]},"properties":{"name":"Famalicao da Nazare","UICIBNR":9463180,"DBIBNR":9400690,"abkuerzung":"ZARE","countryCode":"PT"}}}
{"_index":"bahnhoefept","_type":"bahnhofpt","_id":"AWYKOlu1xpPIvaVA5Ath","_score":1,"_source":{"type":"Feature","geometry":{"type":"Point","coordinates":[-7.9397869,37.0184476]},"properties":{"name":"Faro(P)","UICIBNR":9473007,"DBIBNR":9400033,"abkuerzung":"AROP","countryCode":"PT"}}}
{"_index":"bahnhoefept","_type":"bahnhofpt","_id":"AWYKOlu2xpPIvaVA5Ati","_score":1,"_source":{"type":"Feature","geometry":{"type":"Point","coordinates":[-7.410554,40.14943]},"properties":{"name":"Fatela-Penamacor","UICIBNR":9453462,"DBIBNR":9400305,"abkuerzung":"ACOR","countryCode":"PT"}}}
{"_index":"bahnhoefept","_type":"bahnhofpt","_id":"AWYKOlu2xpPIvaVA5Atr","_score":1,"_source":{"type":"Feature","geometry":{"type":"Point","coordinates":[-8.813806,40.14196]},"properties":{"name":"Fontela","UICIBNR":9464089,"DBIBNR":9400035,"abkuerzung":"TELA","countryCode":"PT"}}}
{"_index":"bahnhoefept","_type":"bahnhofpt","_id":"AWYKOlu2xpPIvaVA5Atv","_score":1,"_source":{"type":"Feature","geometry":{"type":"Point","coordinates":[-8.6474807,41.0815672]},"properties":{"name":"Francelos","UICIBNR":9439081,"DBIBNR":9400323,"abkuerzung":"ELOS","countryCode":"PT"}}}
{"_index":"bahnhoefept","_type":"bahnhofpt","_id":"AWYKOlu2xpPIvaVA5At6","_score":1,"_source":{"type":"Feature","geometry":{"type":"Point","coordinates":[-8.3881822,41.3647046]},"properties":{"name":"Giesteira","UICIBNR":9428159,"DBIBNR":9400338,"abkuerzung":"EIRA","countryCode":"PT"}}}
{"_index":"bahnhoefept","_type":"bahnhofpt","_id":"AWYKOlu2xpPIvaVA5AuD","_score":1,"_source":{"type":"Feature","geometry":{"type":"Point","coordinates":[-8.3423427,41.1810344]},"properties":{"name":"Irivo","UICIBNR":9408243,"DBIBNR":9400347,"abkuerzung":"RIVO","countryCode":"PT"}}}
{"_index":"bahnhoefept","_type":"bahnhofpt","_id":"AWYKOlu2xpPIvaVA5AuH","_score":1,"_source":{"type":"Feature","geometry":{"type":"Point","coordinates":[-8.4687439,39.5281105]},"properties":{"name":"Lamarosa","UICIBNR":9434090,"DBIBNR":9400351,"abkuerzung":"ROSA","countryCode":"PT"}}}
{"_index":"bahnhoefept","_type":"bahnhofpt","_id":"AWYKOlu2xpPIvaVA5AuK","_score":1,"_source":{"type":"Feature","geometry":{"type":"Point","coordinates":[-7.440911,39.988622]},"properties":{"name":"Lardosa","UICIBNR":9453215,"DBIBNR":9400355,"abkuerzung":"DOSA","countryCode":"PT"}}}
{"_index":"bahnhoefept","_type":"bahnhofpt","_id":"AWYKOlu2xpPIvaVA5AuL","_score":1,"_source":{"type":"Feature","geometry":{"type":"Point","coordinates":[-8.77767,40.125815]},"properties":{"name":"Lares","UICIBNR":9464055,"DBIBNR":9400356,"abkuerzung":"ARES","countryCode":"PT"}}}
{"_index":"bahnhoefept","_type":"bahnhofpt","_id":"AWYKOlu2xpPIvaVA5AuP","_score":1,"_source":{"type":"Feature","geometry":{"type":"Point","coordinates":[-8.8277112,39.756529]},"properties":{"name":"Leiria","UICIBNR":9463560,"DBIBNR":9400039,"abkuerzung":"IRIA","countryCode":"PT"}}}
{"_index":"bahnhoefept","_type":"bahnhofpt","_id":"AWYKOlu2xpPIvaVA5AuV","_score":1,"_source":{"type":"Feature","geometry":{"type":"Point","coordinates":[-8.81484,40.014663]},"properties":{"name":"Lourical","UICIBNR":9463875,"DBIBNR":9400369,"abkuerzung":"ICAL","countryCode":"PT"}}}
{"_index":"bahnhoefept","_type":"bahnhofpt","_id":"AWYKOlu2xpPIvaVA5AuW","_score":1,"_source":{"type":"Feature","geometry":{"type":"Point","coordinates":[-8.5378637,41.4367338]},"properties":{"name":"Louro","UICIBNR":9405116,"DBIBNR":9400370,"abkuerzung":"OURO","countryCode":"PT"}}}
{"_index":"bahnhoefept","_type":"bahnhofpt","_id":"AWYKOlu2xpPIvaVA5AuX","_score":1,"_source":{"type":"Feature","geometry":{"type":"Point","coordinates":[-8.5268531,41.3511149]},"properties":{"name":"Lousado","UICIBNR":9405009,"DBIBNR":9400373,"abkuerzung":"SADO","countryCode":"PT"}}}
{"_index":"bahnhoefept","_type":"bahnhofpt","_id":"AWYKOlu2xpPIvaVA5Auf","_score":1,"_source":{"type":"Feature","geometry":{"type":"Point","coordinates":[-8.136861,41.180986]},"properties":{"name":"Marco de Canaveses","UICIBNR":9409001,"DBIBNR":9400387,"abkuerzung":"ESES","countryCode":"PT"}}}
{"_index":"bahnhoefept","_type":"bahnhofpt","_id":"AWYKOlu3xpPIvaVA5Aun","_score":1,"_source":{"type":"Feature","geometry":{"type":"Point","coordinates":[-8.4537017,40.375422]},"properties":{"name":"Mealhada","UICIBNR":9437051,"DBIBNR":9400396,"abkuerzung":"HADA","countryCode":"PT"}}}
{"_index":"bahnhoefept","_type":"bahnhofpt","_id":"AWYKOlu3xpPIvaVA5Auo","_score":1,"_source":{"type":"Feature","geometry":{"type":"Point","coordinates":[-8.6477991,37.1184565]},"properties":{"name":"Meia-Praia","UICIBNR":9490431,"DBIBNR":9400397,"abkuerzung":"RAIA","countryCode":"PT"}}}
{"_index":"bahnhoefept","_type":"bahnhofpt","_id":"AWYKOlu3xpPIvaVA5Auq","_score":1,"_source":{"type":"Feature","geometry":{"type":"Point","coordinates":[-9.3307048,38.793327]},"properties":{"name":"Mercês","UICIBNR":9461051,"DBIBNR":9400401,"abkuerzung":"RCES","countryCode":"PT"}}}
{"_index":"bahnhoefept","_type":"bahnhofpt","_id":"AWYKOlu3xpPIvaVA5Aur","_score":1,"_source":{"type":"Feature","geometry":{"type":"Point","coordinates":[-8.2908136,37.2555043]},"properties":{"name":"Messines-Alte","UICIBNR":9477735,"DBIBNR":9400402,"abkuerzung":"ALTE","countryCode":"PT"}}}
{"_index":"bahnhoefept","_type":"bahnhofpt","_id":"AWYKOlu3xpPIvaVA5Auz","_score":1,"_source":{"type":"Feature","geometry":{"type":"Point","coordinates":[-8.4595152,40.4504308]},"properties":{"name":"Mogofores","UICIBNR":9437143,"DBIBNR":9400412,"abkuerzung":"ORES","countryCode":"PT"}}}
{"_index":"bahnhoefept","_type":"bahnhofpt","_id":"AWYKOlu3xpPIvaVA5Au2","_score":1,"_source":{"type":"Feature","geometry":{"type":"Point","coordinates":[-8.8643085,41.8479133]},"properties":{"name":"Moledo do Minho","UICIBNR":9418200,"DBIBNR":9400415,"abkuerzung":"INHO","countryCode":"PT"}}}
{"_index":"bahnhoefept","_type":"bahnhofpt","_id":"AWYKOlu3xpPIvaVA5Au4","_score":1,"_source":{"type":"Feature","geometry":{"type":"Point","coordinates":[-8.6254913,40.9822751]},"properties":{"name":"Monte de Paramos","UICIBNR":9444040,"DBIBNR":9400419,"abkuerzung":"AMOS","countryCode":"PT"}}}
{"_index":"bahnhoefept","_type":"bahnhofpt","_id":"AWYKOlu3xpPIvaVA5Au-","_score":1,"_source":{"type":"Feature","geometry":{"type":"Point","coordinates":[-8.2411064,40.3909097]},"properties":{"name":"Mortágua","UICIBNR":9446243,"DBIBNR":9400003,"abkuerzung":"AGUA","countryCode":"PT"}}}
{"_index":"bahnhoefept","_type":"bahnhofpt","_id":"AWYKOlu3xpPIvaVA5AvD","_score":1,"_source":{"type":"Feature","geometry":{"type":"Point","coordinates":[-8.100009,39.477873]},"properties":{"name":"Mouriscas-A","UICIBNR":9452167,"DBIBNR":9400432,"abkuerzung":"CASA","countryCode":"PT"}}}
{"_index":"bahnhoefept","_type":"bahnhofpt","_id":"AWYKOlu3xpPIvaVA5AvG","_score":1,"_source":{"type":"Feature","geometry":{"type":"Point","coordinates":[-8.5442813,41.4547549]},"properties":{"name":"Nine","UICIBNR":9406007,"DBIBNR":9400437,"abkuerzung":"NINE","countryCode":"PT"}}}
{"_index":"bahnhoefept","_type":"bahnhofpt","_id":"AWYKOlu3xpPIvaVA5AvN","_score":1,"_source":{"type":"Feature","geometry":{"type":"Point","coordinates":[-8.481793,40.840166]},"properties":{"name":"Oliveira de Azeméis","UICIBNR":9444339,"DBIBNR":9400446,"abkuerzung":"MEIS","countryCode":"PT"}}}
{"_index":"bahnhoefept","_type":"bahnhofpt","_id":"AWYKOlu3xpPIvaVA5AvQ","_score":1,"_source":{"type":"Feature","geometry":{"type":"Point","coordinates":[-8.4767239,40.5721633]},"properties":{"name":"Oronhe","UICIBNR":9442176,"DBIBNR":9400451,"abkuerzung":"ONHE","countryCode":"PT"}}}
{"_index":"bahnhoefept","_type":"bahnhofpt","_id":"AWYKOlu3xpPIvaVA5AvT","_score":1,"_source":{"type":"Feature","geometry":{"type":"Point","coordinates":[-9.2909784,38.6971485]},"properties":{"name":"Paço de Arcos","UICIBNR":9469146,"DBIBNR":9400457,"abkuerzung":"RCOS","countryCode":"PT"}}}
{"_index":"bahnhoefept","_type":"bahnhofpt","_id":"AWYKOlu3xpPIvaVA5AvV","_score":1,"_source":{"type":"Feature","geometry":{"type":"Point","coordinates":[-8.4739738,39.5799737]},"properties":{"name":"Paialvo","UICIBNR":9434157,"DBIBNR":9400459,"abkuerzung":"ALVO","countryCode":"PT"}}}
{"_index":"bahnhoefept","_type":"bahnhofpt","_id":"AWYKOlu3xpPIvaVA5AvW","_score":1,"_source":{"type":"Feature","geometry":{"type":"Point","coordinates":[-8.0905856,41.1035397]},"properties":{"name":"Pala","UICIBNR":9409100,"DBIBNR":9400460,"abkuerzung":"PALA","countryCode":"PT"}}}
{"_index":"bahnhoefept","_type":"bahnhofpt","_id":"AWYKOlu3xpPIvaVA5AvY","_score":1,"_source":{"type":"Feature","geometry":{"type":"Point","coordinates":[-8.4312102,40.3381298]},"properties":{"name":"Pampilhosa","UICIBNR":9437002,"DBIBNR":9400013,"abkuerzung":"HOSA","countryCode":"PT"}}}
{"_index":"bahnhoefept","_type":"bahnhofpt","_id":"AWYKOlu3xpPIvaVA5Ava","_score":1,"_source":{"type":"Feature","geometry":{"type":"Point","coordinates":[-8.3721937,41.1601461]},"properties":{"name":"Parada","UICIBNR":9408201,"DBIBNR":9400465,"abkuerzung":"RADA","countryCode":"PT"}}}
{"_index":"bahnhoefept","_type":"bahnhofpt","_id":"AWYKOlu3xpPIvaVA5Avg","_score":1,"_source":{"type":"Feature","geometry":{"type":"Point","coordinates":[-8.98515,39.655302]},"properties":{"name":"Pataias","UICIBNR":9463354,"DBIBNR":9400472,"abkuerzung":"AIAS","countryCode":"PT"}}}
{"_index":"bahnhoefept","_type":"bahnhofpt","_id":"AWYKOlu4xpPIvaVA5Avl","_score":1,"_source":{"type":"Feature","geometry":{"type":"Point","coordinates":[-8.6330942,39.967513]},"properties":{"name":"Pelariga","UICIBNR":9434702,"DBIBNR":9400478,"abkuerzung":"RIGA","countryCode":"PT"}}}
{"_index":"bahnhoefept","_type":"bahnhofpt","_id":"AWYKOlu4xpPIvaVA5Avy","_score":1,"_source":{"type":"Feature","geometry":{"type":"Point","coordinates":[-8.5487696,41.300859]},"properties":{"name":"Portela","UICIBNR":9404101,"DBIBNR":9400495,"abkuerzung":"TELA","countryCode":"PT"}}}
{"_index":"bahnhoefept","_type":"bahnhofpt","_id":"AWYKOlu4xpPIvaVA5Av2","_score":1,"_source":{"type":"Feature","geometry":{"type":"Point","coordinates":[-9.064336,38.859325]},"properties":{"name":"Povoa","UICIBNR":9431146,"DBIBNR":9400497,"abkuerzung":"OVOA","countryCode":"PT"}}}
{"_index":"bahnhoefept","_type":"bahnhofpt","_id":"AWYKOlu4xpPIvaVA5Av8","_score":1,"_source":{"type":"Feature","geometry":{"type":"Point","coordinates":[-9.216038,39.1398035]},"properties":{"name":"Ramalhal","UICIBNR":9462547,"DBIBNR":9400510,"abkuerzung":"LHAL","countryCode":"PT"}}}
{"_index":"bahnhoefept","_type":"bahnhofpt","_id":"AWYKOlu4xpPIvaVA5Av9","_score":1,"_source":{"type":"Feature","geometry":{"type":"Point","coordinates":[-9.2227767,38.7507924]},"properties":{"name":"Reboleira","UICIBNR":9460095,"DBIBNR":9400682,"abkuerzung":"EIRA","countryCode":"PT"}}}
{"_index":"bahnhoefept","_type":"bahnhofpt","_id":"AWYKOlu4xpPIvaVA5Av_","_score":1,"_source":{"type":"Feature","geometry":{"type":"Point","coordinates":[-8.1752548,41.2315609]},"properties":{"name":"Recesinhos","UICIBNR":9408441,"DBIBNR":9400513,"abkuerzung":"NHOS","countryCode":"PT"}}}
{"_index":"bahnhoefept","_type":"bahnhofpt","_id":"AWYKOlu4xpPIvaVA5AwD","_score":1,"_source":{"type":"Feature","geometry":{"type":"Point","coordinates":[-7.591471,39.769465]},"properties":{"name":"Retaxo","UICIBNR":9452845,"DBIBNR":9400517,"abkuerzung":"TAXO","countryCode":"PT"}}}
{"_index":"bahnhoefept","_type":"bahnhofpt","_id":"AWYKOlu4xpPIvaVA5AwE","_score":1,"_source":{"type":"Feature","geometry":{"type":"Point","coordinates":[-8.74556,40.131649]},"properties":{"name":"Reveles","UICIBNR":9465128,"DBIBNR":9400518,"abkuerzung":"ELES","countryCode":"PT"}}}
{"_index":"bahnhoefept","_type":"bahnhofpt","_id":"AWYKOlu4xpPIvaVA5AwH","_score":1,"_source":{"type":"Feature","geometry":{"type":"Point","coordinates":[-8.5708065,40.9610295]},"properties":{"name":"Rio Meão","UICIBNR":9444115,"DBIBNR":9400523,"abkuerzung":"MEAO","countryCode":"PT"}}}
{"_index":"bahnhoefept","_type":"bahnhofpt","_id":"AWYKOlu4xpPIvaVA5AwJ","_score":1,"_source":{"type":"Feature","geometry":{"type":"Point","coordinates":[-7.09055,40.5070084]},"properties":{"name":"Rochoso","UICIBNR":9449163,"DBIBNR":9400525,"abkuerzung":"HOSO","countryCode":"PT"}}}
{"_index":"bahnhoefept","_type":"bahnhofpt","_id":"AWYKOlu4xpPIvaVA5AwM","_score":1,"_source":{"type":"Feature","geometry":{"type":"Point","coordinates":[-9.2998981,38.8309404]},"properties":{"name":"Sabugo","UICIBNR":9462091,"DBIBNR":9400545,"abkuerzung":"BUGO","countryCode":"PT"}}}
{"_index":"bahnhoefept","_type":"bahnhofpt","_id":"AWYKOlu4xpPIvaVA5AwN","_score":1,"_source":{"type":"Feature","geometry":{"type":"Point","coordinates":[-9.094637,38.806692]},"properties":{"name":"Sacavem/Bobadela Sul","UICIBNR":9431062,"DBIBNR":9400546,"abkuerzung":"ASUL","countryCode":"PT"}}}
{"_index":"bahnhoefept","_type":"bahnhofpt","_id":"AWYKOlu4xpPIvaVA5AwS","_score":1,"_source":{"type":"Feature","geometry":{"type":"Point","coordinates":[-8.3934153,39.5527804]},"properties":{"name":"Santa Cita","UICIBNR":9440105,"DBIBNR":9400555,"abkuerzung":"CITA","countryCode":"PT"}}}
{"_index":"bahnhoefept","_type":"bahnhofpt","_id":"AWYKOlu5xpPIvaVA5Awt","_score":1,"_source":{"type":"Feature","geometry":{"type":"Point","coordinates":[-8.4526332,40.6722509]},"properties":{"name":"Sernada do Vouga","UICIBNR":9443000,"DBIBNR":9400572,"abkuerzung":"OUGA","countryCode":"PT"}}}
{"_index":"bahnhoefept","_type":"bahnhofpt","_id":"AWYKOlu5xpPIvaVA5Awu","_score":1,"_source":{"type":"Feature","geometry":{"type":"Point","coordinates":[-8.7780192,39.1137023]},"properties":{"name":"Setil","UICIBNR":9432003,"DBIBNR":9400575,"abkuerzung":"ETIL","countryCode":"PT"}}}
{"_index":"bahnhoefept","_type":"bahnhofpt","_id":"AWYKOlu5xpPIvaVA5Awx","_score":1,"_source":{"type":"Feature","geometry":{"type":"Point","coordinates":[-8.6406699,40.9903302]},"properties":{"name":"Silvalde","UICIBNR":9438422,"DBIBNR":9400579,"abkuerzung":"ALDE","countryCode":"PT"}}}
{"_index":"bahnhoefept","_type":"bahnhofpt","_id":"AWYKOlu5xpPIvaVA5Awy","_score":1,"_source":{"type":"Feature","geometry":{"type":"Point","coordinates":[-8.6303424,40.9888662]},"properties":{"name":"Silvalde-Vouga","UICIBNR":9444032,"DBIBNR":9400580,"abkuerzung":"OUGA","countryCode":"PT"}}}
{"_index":"bahnhoefept","_type":"bahnhofpt","_id":"AWYKOlu5xpPIvaVA5Aw4","_score":1,"_source":{"type":"Feature","geometry":{"type":"Point","coordinates":[-8.4716712,39.5428769]},"properties":{"name":"Soudos-Vila Nova","UICIBNR":9440014,"DBIBNR":9400586,"abkuerzung":"NOVA","countryCode":"PT"}}}
{"_index":"bahnhoefept","_type":"bahnhofpt","_id":"AWYKOlu5xpPIvaVA5Aw6","_score":1,"_source":{"type":"Feature","geometry":{"type":"Point","coordinates":[-8.4255442,40.2861549]},"properties":{"name":"Souselas","UICIBNR":9436087,"DBIBNR":9400588,"abkuerzung":"ELAS","countryCode":"PT"}}}
{"_index":"bahnhoefept","_type":"bahnhofpt","_id":"AWYKOlu5xpPIvaVA5Aw7","_score":1,"_source":{"type":"Feature","geometry":{"type":"Point","coordinates":[-8.4829899,41.5091977]},"properties":{"name":"Tadim","UICIBNR":9429090,"DBIBNR":9400600,"abkuerzung":"ADIM","countryCode":"PT"}}}
{"_index":"bahnhoefept","_type":"bahnhofpt","_id":"AWYKOlu5xpPIvaVA5AxH","_score":1,"_source":{"type":"Feature","geometry":{"type":"Point","coordinates":[-8.248092,39.460324]},"properties":{"name":"Tramagal","UICIBNR":9451243,"DBIBNR":9400615,"abkuerzung":"AGAL","countryCode":"PT"}}}
{"_index":"bahnhoefept","_type":"bahnhofpt","_id":"AWYKOlu5xpPIvaVA5AxQ","_score":1,"_source":{"type":"Feature","geometry":{"type":"Point","coordinates":[-9.017529,39.584628]},"properties":{"name":"Valado","UICIBNR":9463263,"DBIBNR":9400044,"abkuerzung":"LADO","countryCode":"PT"}}}
{"_index":"bahnhoefept","_type":"bahnhofpt","_id":"AWYKOlu5xpPIvaVA5AxU","_score":1,"_source":{"type":"Feature","geometry":{"type":"Point","coordinates":[-8.6014873,40.8341798]},"properties":{"name":"Válega","UICIBNR":9438240,"DBIBNR":9400647,"abkuerzung":"LEGA","countryCode":"PT"}}}
{"_index":"bahnhoefept","_type":"bahnhofpt","_id":"AWYKOlu5xpPIvaVA5Axb","_score":1,"_source":{"type":"Feature","geometry":{"type":"Point","coordinates":[-8.6521161,39.8508572]},"properties":{"name":"Vermoil","UICIBNR":9434553,"DBIBNR":9400653,"abkuerzung":"MOIL","countryCode":"PT"}}}
{"_index":"bahnhoefept","_type":"bahnhofpt","_id":"AWYKOlu5xpPIvaVA5Axf","_score":1,"_source":{"type":"Feature","geometry":{"type":"Point","coordinates":[-8.5354167,40.924072]},"properties":{"name":"Vila da Feira","UICIBNR":9444206,"DBIBNR":9400662,"abkuerzung":"EIRA","countryCode":"PT"}}}
{"_index":"bahnhoefept","_type":"bahnhofpt","_id":"AWYKOlu5xpPIvaVA5Axi","_score":1,"_source":{"type":"Feature","geometry":{"type":"Point","coordinates":[-7.2582686,40.724832]},"properties":{"name":"Vila Franca das Naves","UICIBNR":9448546,"DBIBNR":9400083,"abkuerzung":"AVES","countryCode":"PT"}}}
{"_index":"bahnhoefept","_type":"bahnhofpt","_id":"AWYKOlu6xpPIvaVA5Axr","_score":1,"_source":{"type":"Feature","geometry":{"type":"Point","coordinates":[-7.4214523,37.1996747]},"properties":{"name":"Vila Real de Santo António","UICIBNR":9473569,"DBIBNR":9400632,"abkuerzung":"ONIO","countryCode":"PT"}}}
{"_index":"bahnhoefept","_type":"bahnhofpt","_id":"AWYKOlu6xpPIvaVA5Axt","_score":1,"_source":{"type":"Feature","geometry":{"type":"Point","coordinates":[-8.4413277,40.2631644]},"properties":{"name":"Vilela-Fornos","UICIBNR":9436053,"DBIBNR":9400667,"abkuerzung":"RNOS","countryCode":"PT"}}}
{"_index":"bahnhoefept","_type":"bahnhofpt","_id":"AWYKOlu6xpPIvaVA5Axv","_score":1,"_source":{"type":"Feature","geometry":{"type":"Point","coordinates":[-8.3125596,41.3790483]},"properties":{"name":"Vizela","UICIBNR":9428233,"DBIBNR":9400669,"abkuerzung":"ZELA","countryCode":"PT"}}}
{"_index":"bahnhoefept","_type":"bahnhofpt","_id":"AWYKOlu6xpPIvaVA5Axx","_score":1,"_source":{"type":"Feature","geometry":{"type":"Point","coordinates":[-9.296683311,38.7640152]},"properties":{"name":"Agualva-Cacem","UICIBNR":9461002,"DBIBNR":null,"abkuerzung":"ACEM","countryCode":"PT"}}}
{"_index":"bahnhoefept","_type":"bahnhofpt","_id":"AWYKOlu6xpPIvaVA5Axy","_score":1,"_source":{"type":"Feature","geometry":{"type":"Point","coordinates":[-8.556505203,41.20056534]},"properties":{"name":"Aguas Santas - Palmilheira","UICIBNR":9403046,"DBIBNR":null,"abkuerzung":"EIRA","countryCode":"PT"}}}
{"_index":"bahnhoefept","_type":"bahnhofpt","_id":"AWYKOlu6xpPIvaVA5Ax1","_score":1,"_source":{"type":"Feature","geometry":{"type":"Point","coordinates":[-9.172848701,38.7075882]},"properties":{"name":"Alcantara-Terra","UICIBNR":9467025,"DBIBNR":null,"abkuerzung":"ERRA","countryCode":"PT"}}}
{"_index":"bahnhoefept","_type":"bahnhofpt","_id":"AWYKOlu6xpPIvaVA5Ax5","_score":1,"_source":{"type":"Feature","geometry":{"type":"Point","coordinates":[-8.866794586,41.81620789]},"properties":{"name":"Ancora Praia","UICIBNR":9418150,"DBIBNR":null,"abkuerzung":"RAIA","countryCode":"PT"}}}
